AUTHORS.txt
CHANGELOG.txt
LICENSE.txt
README.txt
setup.py
Coopr.egg-info/PKG-INFO
Coopr.egg-info/SOURCES.txt
Coopr.egg-info/dependency_links.txt
Coopr.egg-info/requires.txt
Coopr.egg-info/top_level.txt
coopr/__init__.py
coopr/pyomo/__init__.py