Metadata-Version: 1.1
Name: Coopr
Version: 4.0.9597
Summary: Coopr: a COmmon Optimization Python Repository
Home-page: https://software.sandia.gov/coopr
Author: William E. Hart
Author-email: wehart@sandia.gov
License: BSD
Keywords: optimization
Platform: any
Classifier: Development Status :: 4 - Beta
Classifier: Intended Audience :: End Users/Desktop
Classifier: Intended Audience :: Science/Research
Classifier: License :: OSI Approved :: BSD License
Classifier: Natural Language :: English
Classifier: Operating System :: Microsoft :: Windows
Classifier: Operating System :: Unix
Classifier: Programming Language :: Python
Classifier: Programming Language :: Unix Shell
Classifier: Topic :: Scientific/Engineering :: Mathematics
Classifier: Topic :: Software Development :: Libraries :: Python Modules
